simcalibration/__init__.py
simcalibration/main.py
simcalibration/dg_models/Bnlearner.py
simcalibration/dg_models/DGModel.py
simcalibration/dg_models/DagsimModel.py
simcalibration/dg_models/NotearsLearner.py
simcalibration/dg_models/PgmpyLearner.py
simcalibration/dg_models/PomegranateLearner.py
simcalibration/dg_models/WorldLearner.py
simcalibration/ml_models/MachineLearner.py
simcalibration/ml_models/SklearnModel.py
simcalibration/utils/Andes_Dag.py
simcalibration/utils/Data.py
simcalibration/utils/Evaluator.py
simcalibration/utils/Postprocressing.py
simcalibration/utils/Win95_Dag.py
simcalibration/utils/WorldLearner.py
simcalibration/utils/__init__.py
simcalibration-0.1.16.dist-info/LICENSE
simcalibration-0.1.16.dist-info/METADATA
simcalibration-0.1.16.dist-info/WHEEL
simcalibration-0.1.16.dist-info/entry_points.txt
simcalibration-0.1.16.dist-info/top_level.txt
simcalibration-0.1.16.dist-info/RECORD
