Metadata-Version: 2.1
Name: simcalibration
Version: 0.1.16
Summary: Simulation Calibration framework
Author: Mostafa Alwash
Author-email: Mostafa Alwash <malwash@gmail.com>
License: Apache License
Project-URL: Homepage, https://github.com/uio-bmi/SimCal
Project-URL: Issues, https://github.com/uio-bmi/SimCal/issues
Classifier: Programming Language :: Python :: 3
Classifier: License :: OSI Approved :: MIT License
Classifier: Operating System :: POSIX :: Linux
Classifier: Operating System :: MacOS :: MacOS X
Requires-Python: >=3.8
License-File: LICENSE
Requires-Dist: graphviz>=0.20.3
Requires-Dist: numpy>=1.20.2
Requires-Dist: pandas<2.0.0,>=1.5.3
Requires-Dist: igraph==0.11.6
Requires-Dist: scikit-learn==1.3.2
Requires-Dist: scipy>=1.6.2
Requires-Dist: tabulate>=0.8.9
Requires-Dist: bnlearn~=0.8.2
Requires-Dist: dagsim~=1.0.6
Requires-Dist: statsmodels~=0.13.2
Requires-Dist: matplotlib~=3.5.1
Requires-Dist: seaborn>=0.11.2
Requires-Dist: rpy2==3.4.5; platform_system != "Windows"
Provides-Extra: dev
Requires-Dist: ipython>=7.27.0; extra == "dev"
Requires-Dist: pytest>=7; extra == "dev"
Requires-Dist: pytest-cov; extra == "dev"
Requires-Dist: ruff; extra == "dev"
Requires-Dist: black; extra == "dev"
Requires-Dist: build; extra == "dev"
Requires-Dist: twine; extra == "dev"
